web_suck_it_py/__init__.py
web_suck_it_py/base.py
web_suck_it_py/channel.py
web_suck_it_py/constants.py
web_suck_it_py/error.py
web_suck_it_py/request.py
web_suck_it_py/response.py
web_suck_it_py/stubs/web_suck_it_py/__init__.pyi
web_suck_it_py/stubs/web_suck_it_py/base.pyi
web_suck_it_py/stubs/web_suck_it_py/channel.pyi
web_suck_it_py/stubs/web_suck_it_py/constants.pyi
web_suck_it_py/stubs/web_suck_it_py/error.pyi
web_suck_it_py/stubs/web_suck_it_py/request.pyi
web_suck_it_py/stubs/web_suck_it_py/response.pyi
web_suck_it_py/versioned_types.py
web_suck_it_py-0.0.2.dist-info/LICENSE
web_suck_it_py-0.0.2.dist-info/METADATA
web_suck_it_py-0.0.2.dist-info/WHEEL
web_suck_it_py-0.0.2.dist-info/RECORD
